openplaning/__init__.py
openplaning/openplaning.py
openplaning/tables/Raw_0.2.csv
openplaning/tables/Raw_0.4.csv
openplaning/tables/Raw_0.6.csv
openplaning/tables/Raw_V_0.2.csv
openplaning/tables/Raw_V_0.4.csv
openplaning/tables/Raw_V_0.6.csv
openplaning/tables/V_0.2.csv
openplaning/tables/V_0.4.csv
openplaning-0.4.8.dist-info/licenses/LICENSE
openplaning-0.4.8.dist-info/METADATA
openplaning-0.4.8.dist-info/WHEEL
openplaning-0.4.8.dist-info/top_level.txt
openplaning-0.4.8.dist-info/RECORD
