Metadata-Version: 2.4
Name: openplaning
Version: 0.4.8
Summary: Hydrodynamic evaluation of planing hulls based on the Savitsky empirical methods.
Home-page: https://github.com/elcf/python-openplaning
Author: Esteban L. Castro-Feliciano
Author-email: ecastro@crown-hydro.com
Project-URL: Bug Tracker, https://github.com/elcf/python-openplaning/issues
Classifier: Programming Language :: Python :: 3
Classifier: License :: OSI Approved :: MIT License
Classifier: Operating System :: OS Independent
Requires-Python: >=3.6
License-File: LICENSE
Requires-Dist: numpy
Requires-Dist: scipy
Requires-Dist: ndmath
Dynamic: author
Dynamic: author-email
Dynamic: classifier
Dynamic: description
Dynamic: description-content-type
Dynamic: home-page
Dynamic: license-file
Dynamic: project-url
Dynamic: requires-dist
Dynamic: requires-python
Dynamic: summary
